execman/__init__.py
execman/execman.py
execman-1.0.6.dist-info/METADATA
execman-1.0.6.dist-info/WHEEL
execman-1.0.6.dist-info/top_level.txt
execman-1.0.6.dist-info/RECORD
