Metadata-Version: 2.1
Name: execman
Version: 1.0.6
Summary: Cli helper
Home-page: UNKNOWN
Author: jaytrairat
Author-email: <jay.trairat@gmail.com>
License: UNKNOWN
Keywords: jaytrairat
Platform: UNKNOWN
Classifier: Programming Language :: Python :: 3
